event_statemachine/__init__.py
event_statemachine/context.py
event_statemachine/handler.py
event_statemachine/sm.py
event_statemachine-0.0.3.dist-info/AUTHORS.rst
event_statemachine-0.0.3.dist-info/LICENSE
event_statemachine-0.0.3.dist-info/METADATA
event_statemachine-0.0.3.dist-info/WHEEL
event_statemachine-0.0.3.dist-info/top_level.txt
event_statemachine-0.0.3.dist-info/RECORD
