Metadata-Version: 2.1
Name: event-statemachine
Version: 0.0.3
Summary: A simple event driven state machine
Home-page: https://github.com/fedegonzalezit/event_statemachine
Author: Federico Gonzalez Itzik
Author-email: fedelean.gon@gmail.com
License: MIT license
Keywords: event_statemachine
Classifier: Development Status :: 2 - Pre-Alpha
Classifier: Intended Audience :: Developers
Classifier: License :: OSI Approved :: MIT License
Classifier: Natural Language :: English
Classifier: Programming Language :: Python :: 3
Classifier: Programming Language :: Python :: 3.6
Classifier: Programming Language :: Python :: 3.7
Classifier: Programming Language :: Python :: 3.8
Requires-Python: >=3.6
License-File: LICENSE
License-File: AUTHORS.rst
